sigmoda/__init__.py
sigmoda/client.py
sigmoda/config.py
sigmoda/openai_wrapper.py
sigmoda-0.2.1.dist-info/LICENSE
sigmoda-0.2.1.dist-info/METADATA
sigmoda-0.2.1.dist-info/WHEEL
sigmoda-0.2.1.dist-info/top_level.txt
sigmoda-0.2.1.dist-info/RECORD
