Metadata-Version: 2.2
Name: sigmoda
Version: 0.2.1
Summary: Sigmoda Python SDK for logging LLM events and OpenAI chat completions.
Author: Sigmoda
License: MIT License
Project-URL: Homepage, https://sigmoda.com
Project-URL: Repository, https://github.com/seljawhari/sigmoda-python
Classifier: Programming Language :: Python
Classifier: Programming Language :: Python :: 3
Classifier: Programming Language :: Python :: 3 :: Only
Classifier: Programming Language :: Python :: 3.8
Classifier: Programming Language :: Python :: 3.9
Classifier: Programming Language :: Python :: 3.10
Classifier: Programming Language :: Python :: 3.11
Classifier: Programming Language :: Python :: 3.12
Classifier: Intended Audience :: Developers
Classifier: Topic :: Software Development :: Libraries
Requires-Python: >=3.8
License-File: LICENSE
Requires-Dist: requests>=2.28.0
Requires-Dist: openai<3,>=1
Provides-Extra: test
Requires-Dist: pytest>=7.0; extra == "test"
